<?xml version="1.0" encoding="utf-8"?>
<odoo>
    <record id="res_config_settings_view_form_inherit_fish_farm" model="ir.ui.view">
        <field name="name">res.config.settings.view.form.inherit.fish.farm</field>
        <field name="model">res.config.settings</field>
        <field name="inherit_id" ref="base_setup.res_config_settings_view_form"/>
        <field name="arch" type="xml">

            <!-- ندرج إعداداتنا بعد إعداد "Company Registry" الموجود أصلًا -->
            <xpath expr="//setting[@id='base_setup.setting_company_registry']" position="after">

                <!-- Default Feed Product -->
                <setting id="fish_farm.setting_default_feed"
                         string="Default Feed Product"
                         help="Product used by default when registering feed consumption.">
                    <field name="default_feed_product_id"/>
                </setting>

                <!-- Default Medicine Product -->
                <setting id="fish_farm.setting_default_medicine"
                         string="Default Medicine Product"
                         help="Product used by default for pond treatments.">
                    <field name="default_medicine_product_id"/>
                </setting>

                <!-- Harvest Committee Size -->
                <setting id="fish_farm.setting_committee_size"
                         string="Harvest Committee Size"
                         help="Default number of members in the harvest committee.">
                    <field name="harvest_committee_size"/>
                </setting>

                <!-- Analytic Account Prefix -->
                <setting id="fish_farm.setting_account_prefix"
                         string="Analytic Account Prefix"
                         help="Prefix used when system creates analytic accounts for ponds or farms.">
                    <field name="fish_farm_analytic_account_prefix"/>
                </setting>

                <!-- Default Income / Expense Accounts -->
                <setting id="fish_farm.setting_income_account"
                         string="Default Income Account"
                         help="Used when posting revenue from fish harvest.">
                    <field name="default_income_account_id"/>
                </setting>

                <setting id="fish_farm.setting_expense_account"
                         string="Default Expense Account"
                         help="Used when posting feed, medicine, and other costs.">
                    <field name="default_expense_account_id"/>
                </setting>

                <!-- Cost parameters -->
                <setting id="fish_farm.setting_labor_cost"
                         string="Labor Cost per Hour"/>
                    <field name="labor_cost_per_hour"/>
                </setting>

                <setting id="fish_farm.setting_electricity_cost"
                         string="Electricity Cost per kWh"/>
                    <field name="electricity_cost_per_kwh"/>
                </setting>

                <!-- API Integration toggle -->
                <setting id="fish_farm.setting_api_toggle"
                         string="Enable API Integration"
                         help="Allow external systems to retrieve fish-farm data via API.">
                    <field name="enable_api_integration"/>
                </setting>

                <setting id="fish_farm.setting_api_key"
                         string="API Key"
                         help="Shared secret used by external systems.">
                    <field name="api_key" password="True"/>
                </setting>

            </xpath>
        </field>
    </record>
</odoo>
